{
  "metadata": {
    "title": "吨镁成本分析",
    "period": "2026年1-4月累计",
    "unit": "元/吨精镁",
    "extracted_at": "2026-06-10 15:01",
    "source_file": "cost_analysis.xlsx",
    "sheet": "cost_analysis",
    "key_metrics": {
      "料镁比": {
        "value": 6.82,
        "unit": "吨料球/吨镁",
        "decomposition": {
          "煅白": 5.65,
          "75#硅铁": 1.15,
          "萤石粉": 0.02
        }
      },
      "罐耗": {
        "value": 0.3705,
        "unit": "支/吨镁",
        "unit_price": 2600,
        "unit_price_unit": "元/支"
      },
      "硅耗": {
        "value": 1.15,
        "unit": "吨硅铁/吨镁",
        "unit_price": 5874.28,
        "unit_price_unit": "元/吨硅铁"
      },
      "白云石单耗": {
        "value": 11.0,
        "unit": "吨白云石/吨镁",
        "煅白收率": 0.5136,
        "煅白单耗": 5.65,
        "unit_price": 23.56,
        "unit_price_unit": "元/吨白云石"
      },
      "还原车间作业时间": {
        "value": 14,
        "unit": "小时/炉",
        "说明": "还原车间每炉作业时间，缩短可等比例减少煤气消耗"
      },
      "精炼回收率": {
        "value": 0.91,
        "unit": "精镁/粗镁",
        "说明": "当前回收率91%，行业平均97%。提升可等比例减少所有上游物料和能源消耗",
        "可节约": "提升至97%可节约全部成本约6.2%"
      }
    }
  },
  "total_unit_cost": 16711.4594877001,
  "categories": [
    {
      "name": "材料费",
      "unit_cost": 8674.35421601653,
      "sub_items": [
        {
          "name": "白云石",
          "unit_cost": 259.202069619525,
          "单耗": 11.0,
          "单耗单位": "吨白云石/吨镁",
          "可节约": "料镁比降至6.3可节约21.56元/吨镁"
        },
        {
          "name": "75#硅铁",
          "unit_cost": 6755.42072873144,
          "可节约": "硅耗降至1.1可节约293.71元/吨镁",
          "单耗": 1.15,
          "单耗单位": "吨硅铁/吨镁"
        },
        {
          "name": "萤石粉",
          "unit_cost": 287.015359465454,
          "单耗": 0.02,
          "单耗单位": "吨萤石粉/吨镁",
          "备注": "固定消耗量"
        },
        {
          "name": "还原罐",
          "unit_cost": 963.304566574216,
          "可节约": "罐耗降至0.2支/吨镁可节约443.3元/吨镁"
        },
        {
          "name": "二号溶剂",
          "unit_cost": 131.219274125391
        },
        {
          "name": "硫磺粉",
          "unit_cost": 0.0
        },
        {
          "name": "精炼锅",
          "unit_cost": 56.717137449559
        },
        {
          "name": "氯化镁",
          "unit_cost": 221.475080050947
        }
      ],
      "order": "一"
    },
    {
      "name": "备品、备件",
      "unit_cost": 498.053436073648,
      "sub_items": [],
      "order": "二"
    },
    {
      "name": "直接动力费",
      "unit_cost": 4449.04494359732,
      "sub_items": [
        {
          "name": "电",
          "unit_cost": 680.674213477127
        },
        {
          "name": "煤气",
          "unit_cost": 3768.37073012019
        }
      ],
      "order": "三"
    },
    {
      "name": "直接人工费",
      "unit_cost": 2181.62543431193,
      "sub_items": [],
      "order": "四"
    },
    {
      "name": "制造费用",
      "unit_cost": 804.42434199481,
      "sub_items": [
        {
          "name": "安全经费",
          "unit_cost": 103.957115705857
        }
      ],
      "order": "五"
    },
    {
      "name": "折旧与摊销",
      "unit_cost": null,
      "sub_items": [],
      "order": "六"
    }
  ],
  "energy_breakdown": {
    "数据来源": "energy.csv（2021-2025五年平均）",
    "电力": {
      "总单耗": 1885.65,
      "单耗单位": "kwh/吨镁",
      "总成本": 680.67,
      "工段分摊": [
        {
          "name": "煅烧车间",
          "单耗": 339.64,
          "单耗单位": "kwh/吨镁",
          "比例": 0.1801,
          "分摊成本": 122.59,
          "折标煤(kgce/t)": 41.74,
          "折标系数": 0.1229
        },
        {
          "name": "制球车间",
          "单耗": 451.53,
          "单耗单位": "kwh/吨镁",
          "比例": 0.2395,
          "分摊成本": 163.02,
          "折标煤(kgce/t)": 55.49,
          "折标系数": 0.1229
        },
        {
          "name": "还原车间",
          "单耗": 1017.06,
          "单耗单位": "kwh/吨镁",
          "比例": 0.5394,
          "分摊成本": 367.16,
          "折标煤(kgce/t)": 125.0,
          "折标系数": 0.1229
        },
        {
          "name": "精炼车间",
          "单耗": 77.42,
          "单耗单位": "kwh/吨镁",
          "比例": 0.0411,
          "分摊成本": 27.98,
          "折标煤(kgce/t)": 9.51,
          "折标系数": 0.1229
        }
      ]
    },
    "煤气": {
      "总单耗": 7536.74,
      "单耗单位": "m3/吨镁",
      "总成本": 3768.37,
      "工段分摊": [
        {
          "name": "煅烧车间",
          "单耗": 2405.31,
          "单耗单位": "m3/吨镁",
          "比例": 0.3191,
          "分摊成本": 1202.65,
          "折标煤(kgce/t)": 1392.67,
          "折标系数": 0.579
        },
        {
          "name": "还原车间",
          "单耗": 4531.12,
          "单耗单位": "m3/吨镁",
          "比例": 0.6012,
          "分摊成本": 2265.56,
          "折标煤(kgce/t)": 2623.52,
          "折标系数": 0.579,
          "可节约_炉时": "作业时间14→12小时/炉，可再节约煤气647.3m3/t（323.65元/吨镁）"
        },
        {
          "name": "烘炉",
          "单耗": 91.26,
          "单耗单位": "m3/吨镁",
          "比例": 0.0121,
          "分摊成本": 45.63,
          "折标煤(kgce/t)": 52.84,
          "折标系数": 0.579
        },
        {
          "name": "精炼车间",
          "单耗": 509.05,
          "单耗单位": "m3/吨镁",
          "比例": 0.0675,
          "分摊成本": 254.53,
          "折标煤(kgce/t)": 294.74,
          "折标系数": 0.579
        }
      ],
      "煤气单价": 0.5,
      "煤气单价单位": "元/m3"
    },
    "工段说明": {
      "煅烧车间": "使用煤气将白云石煅烧成煅白",
      "制球车间": "将煅白、硅铁和萤石粉粉碎混合制成料球（一般不耗煤气）",
      "还原车间": "将料球用煤气烧出粗镁",
      "精炼车间": "用煤气将粗镁重新熔炼，精炼成纯度更高的成品镁锭",
      "烘炉": "烘炉煤气消耗，为精炼炉保温/预热用"
    },
    "折标系数": {
      "电力": {
        "系数": 0.1229,
        "单位": "kgce/kWh",
        "来源": "GB/T 2589-2020 当量值"
      },
      "焦炉煤气": {
        "系数": 0.579,
        "单位": "kgce/m3",
        "来源": "根据能耗.csv 2021-2025含白灰综合能耗数据反推"
      }
    },
    "工段综合能耗": {
      "单位": "kgce/吨镁",
      "合计": 4595.51,
      "备注": "当前实际消耗水平的折标煤值（煤气按7,536.74 m3/t计算）",
      "工段明细": {
        "煅烧车间": {
          "折标煤": 1434.41,
          "占比": "31.2%"
        },
        "制球车间": {
          "折标煤": 55.49,
          "占比": "1.2%"
        },
        "还原车间": {
          "折标煤": 2748.52,
          "占比": "59.8%"
        },
        "精炼车间": {
          "折标煤": 304.25,
          "占比": "6.6%"
        },
        "烘炉": {
          "折标煤": 52.84,
          "占比": "1.1%"
        }
      }
    }
  }
}